QuectelAT/__init__.py
quectel_at-1.1.0.dist-info/METADATA
quectel_at-1.1.0.dist-info/WHEEL
quectel_at-1.1.0.dist-info/top_level.txt
quectel_at-1.1.0.dist-info/RECORD
