Metadata-Version: 2.2
Name: quectel_at
Version: 1.1.0
Summary: This is a library for Quectel Modules.
Home-page: https://github.com/burakcanturk/Quectel-5G-LTE-Module-Library.git
Author: Burak Cantürk
Author-email: burakcanturk12@gmail.com
Classifier: Programming Language :: Python :: 3
Classifier: License :: OSI Approved :: MIT License
Classifier: Operating System :: OS Independent
Requires-Dist: pyserial
Dynamic: author
Dynamic: author-email
Dynamic: classifier
Dynamic: description
Dynamic: description-content-type
Dynamic: home-page
Dynamic: requires-dist
Dynamic: summary
